{
  "botname":"KevBot",
  "season":2022,
  "round":17,
  "tips": [
    { 
    "home":"Brisbane Lions",
    "away":"Essendon",
    "winner":"Brisbane Lions",
    "margin":32,
    "probability":0.79
    }
    ,
    { 
    "home":"Collingwood",
    "away":"North Melbourne",
    "winner":"Collingwood",
    "margin":43,
    "probability":0.88
    }
    ,
    { 
    "home":"Geelong",
    "away":"Melbourne",
    "winner":"Geelong",
    "margin":4,
    "probability":0.54
    }
    ,
    { 
    "home":"Gold Coast",
    "away":"Richmond",
    "winner":"Gold Coast",
    "margin":1,
    "probability":0.52
    }
    ,
    { 
    "home":"Hawthorn",
    "away":"Adelaide",
    "winner":"Hawthorn",
    "margin":15,
    "probability":0.64
    }
    ,
    { 
    "home":"St Kilda",
    "away":"Fremantle",
    "winner":"St Kilda",
    "margin":3,
    "probability":0.54
    }
    ,
    { 
    "home":"Sydney",
    "away":"Western Bulldogs",
    "winner":"Sydney",
    "margin":10,
    "probability":0.60
    }
    ,
    { 
    "home":"Port Adelaide",
    "away":"Greater Western Sydney",
    "winner":"Port Adelaide",
    "margin":15,
    "probability":0.64
    }
    ,
    { 
    "home":"West Coast",
    "away":"Carlton",
    "winner":"Carlton",
    "margin":23,
    "probability":0.71
    }
  ]
}
