{
  "botname":"ZaphBot2-TipsBits",
  "season":2025,
  "round":19,
  "BestTips":"673",
  "BestTipsBits":"135.727834",
  "BestMargins":"26595",
  "BestRMSE":"33.968206",
  "tips": [
    { 
    "home":"Adelaide",
    "away":"Gold Coast",
    "winner":"Adelaide",
    "margin":14,
    "probability":0.63
    }
    ,
    { 
    "home":"Geelong",
    "away":"St Kilda",
    "winner":"Geelong",
    "margin":35,
    "probability":0.81
    }
    ,
    { 
    "home":"Essendon",
    "away":"Greater Western Sydney",
    "winner":"Greater Western Sydney",
    "margin":30,
    "probability":0.77
    }
    ,
    { 
    "home":"Carlton",
    "away":"Melbourne",
    "winner":"Melbourne",
    "margin":7,
    "probability":0.57
    }
    ,
    { 
    "home":"Collingwood",
    "away":"Fremantle",
    "winner":"Collingwood",
    "margin":6,
    "probability":0.56
    }
    ,
    { 
    "home":"West Coast",
    "away":"Richmond",
    "winner":"West Coast",
    "margin":10,
    "probability":0.60
    }
    ,
    { 
    "home":"Sydney",
    "away":"North Melbourne",
    "winner":"Sydney",
    "margin":35,
    "probability":0.81
    }
    ,
    { 
    "home":"Brisbane Lions",
    "away":"Western Bulldogs",
    "winner":"Brisbane Lions",
    "margin":1,
    "probability":0.52
    }
    ,
    { 
    "home":"Hawthorn",
    "away":"Port Adelaide",
    "winner":"Hawthorn",
    "margin":26,
    "probability":0.74
    }
  ]
}
